.gitignore
.gitlab-ci.yml
.pre-commit-config.yaml
.readthedocs.yml
AUTHORS
CHANGELOG.md
CONTRIBUTING.md
COPYING
LICENSE
NOTICE
README.md
publish_release_to_zenodo.py
pyproject.toml
setup.cfg
setup.py
zenodo_meta.json
bamboo/__init__.py
bamboo/analysismodules.py
bamboo/analysisutils.py
bamboo/batch.py
bamboo/batch_htcondor.py
bamboo/batch_slurm.py
bamboo/dataframebackend.py
bamboo/plots.py
bamboo/root.py
bamboo/scalefactors.py
bamboo/treedecorators.py
bamboo/treefunctions.py
bamboo/treeoperations.py
bamboo/treeproxies.py
bamboo/utils.py
bamboo/workflow.py
bamboo/data/CMakeLists.txt
bamboo/data/FindFilesystem.cmake
bamboo/data/main.cc
bamboo/scripts/__init__.py
bamboo/scripts/bambooRun.py
bamboo/scripts/makePUReWeightJSON.py
bamboo_hep.egg-info/PKG-INFO
bamboo_hep.egg-info/SOURCES.txt
bamboo_hep.egg-info/dependency_links.txt
bamboo_hep.egg-info/entry_points.txt
bamboo_hep.egg-info/requires.txt
bamboo_hep.egg-info/top_level.txt
cpp/bamboohelpers.h
cpp/printprogress.h
cpp/range.h
cpp/scalefactors.h
doc/advanced.rst
doc/apiref.rst
doc/conf.py
doc/hacking.rst
doc/index.rst
doc/install.rst
doc/recipes.rst
doc/rtd-environment.yml
doc/treefunctions.rst
doc/userguide.rst
examples/Cert_271036-284044_13TeV_23Sep2016ReReco_Collisions16_JSON.txt
examples/adl_benchmarks.py
examples/adl_benchmarks.yml
examples/analysis1.yml
examples/analysis_eletnp.yml
examples/analysis_zmm.yml
examples/cern.ini
examples/cmsPhase2Sim.py
examples/cmsPhase2Sim_test.yml
examples/df_nano.py
examples/df_ttW.py
examples/eletnp.py
examples/ingrid.ini
examples/nanozmumu.py
examples/preselectskim.py
examples/test1.yml
examples/test_skim.yml
ext/CMakeLists.txt
ext/Config.cmake.in
ext/install_lwtnn.sh
ext/install_tensorflow-c.sh
ext/cmake/modules/FindONNXRuntime.cmake
ext/cmake/modules/FindTensorflowC.cmake
ext/include/BTagCalibrationStandalone.h
ext/include/BinnedValues.h
ext/include/BinnedValuesJSONParser.h
ext/include/Histogram.h
ext/include/LumiMask.h
ext/include/RoccoR.h
ext/include/RochesterCorrectionCalculator.h
ext/include/bamboolwtnn.h
ext/include/bambooonnxruntime.h
ext/include/bamboorandom.h
ext/include/bamboosofie.h
ext/include/bambootensorflowc.h
ext/include/bambootorch.h
