Metadata-Version: 2.1
Name: bamboo-hep
Version: 1.1.0
Summary: A high-level HEP analysis library for ROOT::RDataFrame
Home-page: https://gitlab.cern.ch/cp3-cms/bamboo
Author: Pieter David
Author-email: pieter.david@cern.ch
License: GPL-3.0-or-later
Keywords: ROOT,RDataFrame
Platform: UNKNOWN
Classifier: Development Status :: 4 - Beta
Classifier: Intended Audience :: Developers
Classifier: Intended Audience :: Science/Research
Classifier: License :: OSI Approved :: GNU General Public License v3 or later (GPLv3+)
Classifier: Operating System :: OS Independent
Classifier: Programming Language :: Python :: 3
Classifier: Programming Language :: Python :: 3 :: Only
Classifier: Programming Language :: Python :: 3.6
Classifier: Programming Language :: Python :: 3.7
Classifier: Programming Language :: Python :: 3.8
Classifier: Programming Language :: Python :: 3.9
Classifier: Programming Language :: Python :: 3.10
Classifier: Topic :: Scientific/Engineering :: Information Analysis
Classifier: Topic :: Scientific/Engineering :: Physics
Classifier: Topic :: Software Development :: Libraries :: Python Modules
Requires-Python: >=3.6
Provides-Extra: cms
Provides-Extra: docs
Provides-Extra: interactive
Provides-Extra: torch
License-File: LICENSE
